cdtools/__init__.py
cdtools/datasets/__init__.py
cdtools/datasets/base.py
cdtools/datasets/ptycho_2d_dataset.py
cdtools/datasets/random_selection.py
cdtools/models/__init__.py
cdtools/models/base.py
cdtools/models/bragg_2d_ptycho.py
cdtools/models/fancy_ptycho.py
cdtools/models/multislice_2d_ptycho.py
cdtools/models/multislice_ptycho.py
cdtools/models/rpi.py
cdtools/models/simple_ptycho.py
cdtools/tools/__init__.py
cdtools/tools/analysis/__init__.py
cdtools/tools/analysis/analysis.py
cdtools/tools/data/__init__.py
cdtools/tools/data/data.py
cdtools/tools/image_processing/__init__.py
cdtools/tools/image_processing/image_processing.py
cdtools/tools/initializers/__init__.py
cdtools/tools/initializers/initializers.py
cdtools/tools/interactions/__init__.py
cdtools/tools/interactions/interactions.py
cdtools/tools/losses/__init__.py
cdtools/tools/losses/losses.py
cdtools/tools/measurements/__init__.py
cdtools/tools/measurements/measurements.py
cdtools/tools/plotting/__init__.py
cdtools/tools/plotting/plotting.py
cdtools/tools/propagators/__init__.py
cdtools/tools/propagators/propagators.py
cdtools_py-0.3.0.dist-info/licenses/LICENSE.txt
cdtools_py-0.3.0.dist-info/METADATA
cdtools_py-0.3.0.dist-info/WHEEL
cdtools_py-0.3.0.dist-info/top_level.txt
cdtools_py-0.3.0.dist-info/RECORD
