Metadata-Version: 2.4
Name: cdtools-py
Version: 0.3.0
Summary: Tools for coherent diffractive imaging and ptychography
Home-page: https://github.mit.edu/scattering/CDTools.git
Author: Abe Levitan
Author-email: abraham.levitan@psi.ch
Classifier: Programming Language :: Python :: 3
Classifier: Operating System :: OS Independent
Requires-Python: >3.8
License-File: LICENSE.txt
Requires-Dist: numpy>=1.0
Requires-Dist: scipy>=1.0
Requires-Dist: matplotlib>=2.0
Requires-Dist: python-dateutil
Requires-Dist: torch>=2.3.0
Requires-Dist: h5py>=2.1
Provides-Extra: tests
Requires-Dist: pytest; extra == "tests"
Requires-Dist: pooch; extra == "tests"
Provides-Extra: docs
Requires-Dist: sphinx>=4.3.0; extra == "docs"
Requires-Dist: sphinx-argparse; extra == "docs"
Requires-Dist: sphinx_rtd_theme>=0.5.1; extra == "docs"
Dynamic: author
Dynamic: author-email
Dynamic: classifier
Dynamic: description
Dynamic: description-content-type
Dynamic: home-page
Dynamic: license-file
Dynamic: provides-extra
Dynamic: requires-dist
Dynamic: requires-python
Dynamic: summary
